{"namedChunkGroups":{"polyfill":{"name":"polyfill","assets":[{"name":"webpack-runtime-29b1c19dd9ccd811faaa.js","size":5542},{"name":"polyfill-0b90e131d8636a6966be.js","size":82663}],"filteredAssets":0,"assetsSize":88205,"filteredAuxiliaryAssets":2,"auxiliaryAssetsSize":222438},"app":{"name":"app","assets":[{"name":"webpack-runtime-29b1c19dd9ccd811faaa.js","size":5542},{"name":"framework-0e025b74e97e392fc0b7.js","size":129951},{"name":"app-ed4be18b1268dfebb8be.js","size":109822}],"filteredAssets":0,"assetsSize":245315,"filteredAuxiliaryAssets":3,"auxiliaryAssetsSize":787218},"component---src-pages-404-js":{"name":"component---src-pages-404-js","assets":[{"name":"styles.b16a86c805a9a5a13ad4.css","size":212497},{"name":"cb1608f2-cc12f6e1b43353c691a1.js","size":2571},{"name":"a9a7754c-65ced6534d0b429b1152.js","size":1672},{"name":"commons-b9df37fa9ae97866a0aa.js","size":73170},{"name":"11a94a3e73140724a8de4b52d94986fe0f3aacd5-91301b22dd8e4c7b9e4b.js","size":15884},{"name":"component---src-pages-404-js-f756e66537292eb692b2.js","size":495}],"filteredAssets":0,"assetsSize":306289,"filteredAuxiliaryAssets":5,"auxiliaryAssetsSize":1643779},"component---src-pages-articulo-a-js":{"name":"component---src-pages-articulo-a-js","assets":[{"name":"styles.b16a86c805a9a5a13ad4.css","size":212497},{"name":"cb1608f2-cc12f6e1b43353c691a1.js","size":2571},{"name":"a9a7754c-65ced6534d0b429b1152.js","size":1672},{"name":"commons-b9df37fa9ae97866a0aa.js","size":73170},{"name":"component---src-pages-articulo-a-js-ef996fbcbeec11d92d48.js","size":894}],"filteredAssets":0,"assetsSize":290804,"filteredAuxiliaryAssets":4,"auxiliaryAssetsSize":1577566},"component---src-pages-index-js":{"name":"component---src-pages-index-js","assets":[{"name":"styles.b16a86c805a9a5a13ad4.css","size":212497},{"name":"cb1608f2-cc12f6e1b43353c691a1.js","size":2571},{"name":"a9a7754c-65ced6534d0b429b1152.js","size":1672},{"name":"commons-b9df37fa9ae97866a0aa.js","size":73170},{"name":"11a94a3e73140724a8de4b52d94986fe0f3aacd5-91301b22dd8e4c7b9e4b.js","size":15884},{"name":"component---src-pages-index-js-82ac5851ccb1bd639f97.js","size":27833}],"filteredAssets":0,"assetsSize":333627,"filteredAuxiliaryAssets":6,"auxiliaryAssetsSize":2664329},"component---src-pages-nosotres-js":{"name":"component---src-pages-nosotres-js","assets":[{"name":"styles.b16a86c805a9a5a13ad4.css","size":212497},{"name":"cb1608f2-cc12f6e1b43353c691a1.js","size":2571},{"name":"a9a7754c-65ced6534d0b429b1152.js","size":1672},{"name":"commons-b9df37fa9ae97866a0aa.js","size":73170},{"name":"component---src-pages-nosotres-js-761dc1512aad9c93ea16.js","size":1737}],"filteredAssets":0,"assetsSize":291647,"filteredAuxiliaryAssets":4,"auxiliaryAssetsSize":1583423},"component---src-pages-page-2-js":{"name":"component---src-pages-page-2-js","assets":[{"name":"styles.b16a86c805a9a5a13ad4.css","size":212497},{"name":"cb1608f2-cc12f6e1b43353c691a1.js","size":2571},{"name":"a9a7754c-65ced6534d0b429b1152.js","size":1672},{"name":"commons-b9df37fa9ae97866a0aa.js","size":73170},{"name":"11a94a3e73140724a8de4b52d94986fe0f3aacd5-91301b22dd8e4c7b9e4b.js","size":15884},{"name":"component---src-pages-page-2-js-88a9f5c879133b486ba5.js","size":532}],"filteredAssets":0,"assetsSize":306326,"filteredAuxiliaryAssets":5,"auxiliaryAssetsSize":1643876},"component---src-pages-publicaciones-js":{"name":"component---src-pages-publicaciones-js","assets":[{"name":"styles.b16a86c805a9a5a13ad4.css","size":212497},{"name":"cb1608f2-cc12f6e1b43353c691a1.js","size":2571},{"name":"a9a7754c-65ced6534d0b429b1152.js","size":1672},{"name":"commons-b9df37fa9ae97866a0aa.js","size":73170},{"name":"component---src-pages-publicaciones-js-960471d7ff4f9e560c4f.js","size":2581}],"filteredAssets":0,"assetsSize":292491,"filteredAuxiliaryAssets":4,"auxiliaryAssetsSize":1582135},"component---src-pages-using-typescript-tsx":{"name":"component---src-pages-using-typescript-tsx","assets":[{"name":"styles.b16a86c805a9a5a13ad4.css","size":212497},{"name":"cb1608f2-cc12f6e1b43353c691a1.js","size":2571},{"name":"a9a7754c-65ced6534d0b429b1152.js","size":1672},{"name":"commons-b9df37fa9ae97866a0aa.js","size":73170},{"name":"11a94a3e73140724a8de4b52d94986fe0f3aacd5-91301b22dd8e4c7b9e4b.js","size":15884},{"name":"component---src-pages-using-typescript-tsx-76ac6780e7b83ea5b8bc.js","size":1342}],"filteredAssets":0,"assetsSize":307136,"filteredAuxiliaryAssets":5,"auxiliaryAssetsSize":1645198}},"assetsByChunkName":{"polyfill":["webpack-runtime-29b1c19dd9ccd811faaa.js","polyfill-0b90e131d8636a6966be.js"],"app":["webpack-runtime-29b1c19dd9ccd811faaa.js","framework-0e025b74e97e392fc0b7.js","app-ed4be18b1268dfebb8be.js"],"component---src-pages-404-js":["styles.b16a86c805a9a5a13ad4.css","cb1608f2-cc12f6e1b43353c691a1.js","a9a7754c-65ced6534d0b429b1152.js","commons-b9df37fa9ae97866a0aa.js","11a94a3e73140724a8de4b52d94986fe0f3aacd5-91301b22dd8e4c7b9e4b.js","component---src-pages-404-js-f756e66537292eb692b2.js"],"component---src-pages-articulo-a-js":["styles.b16a86c805a9a5a13ad4.css","cb1608f2-cc12f6e1b43353c691a1.js","a9a7754c-65ced6534d0b429b1152.js","commons-b9df37fa9ae97866a0aa.js","component---src-pages-articulo-a-js-ef996fbcbeec11d92d48.js"],"component---src-pages-index-js":["styles.b16a86c805a9a5a13ad4.css","cb1608f2-cc12f6e1b43353c691a1.js","a9a7754c-65ced6534d0b429b1152.js","commons-b9df37fa9ae97866a0aa.js","11a94a3e73140724a8de4b52d94986fe0f3aacd5-91301b22dd8e4c7b9e4b.js","component---src-pages-index-js-82ac5851ccb1bd639f97.js"],"component---src-pages-nosotres-js":["styles.b16a86c805a9a5a13ad4.css","cb1608f2-cc12f6e1b43353c691a1.js","a9a7754c-65ced6534d0b429b1152.js","commons-b9df37fa9ae97866a0aa.js","component---src-pages-nosotres-js-761dc1512aad9c93ea16.js"],"component---src-pages-page-2-js":["styles.b16a86c805a9a5a13ad4.css","cb1608f2-cc12f6e1b43353c691a1.js","a9a7754c-65ced6534d0b429b1152.js","commons-b9df37fa9ae97866a0aa.js","11a94a3e73140724a8de4b52d94986fe0f3aacd5-91301b22dd8e4c7b9e4b.js","component---src-pages-page-2-js-88a9f5c879133b486ba5.js"],"component---src-pages-publicaciones-js":["styles.b16a86c805a9a5a13ad4.css","cb1608f2-cc12f6e1b43353c691a1.js","a9a7754c-65ced6534d0b429b1152.js","commons-b9df37fa9ae97866a0aa.js","component---src-pages-publicaciones-js-960471d7ff4f9e560c4f.js"],"component---src-pages-using-typescript-tsx":["styles.b16a86c805a9a5a13ad4.css","cb1608f2-cc12f6e1b43353c691a1.js","a9a7754c-65ced6534d0b429b1152.js","commons-b9df37fa9ae97866a0aa.js","11a94a3e73140724a8de4b52d94986fe0f3aacd5-91301b22dd8e4c7b9e4b.js","component---src-pages-using-typescript-tsx-76ac6780e7b83ea5b8bc.js"]},"childAssetsByChunkName":{}}